CHANGES.txt
CONTRIBUTORS.txt
MANIFEST.in
README.txt
setup.py
docs/LICENSE.GPL
docs/LICENSE.txt
src/raptus/__init__.py
src/raptus.person.egg-info/PKG-INFO
src/raptus.person.egg-info/SOURCES.txt
src/raptus.person.egg-info/dependency_links.txt
src/raptus.person.egg-info/entry_points.txt
src/raptus.person.egg-info/namespace_packages.txt
src/raptus.person.egg-info/not-zip-safe
src/raptus.person.egg-info/requires.txt
src/raptus.person.egg-info/top_level.txt
src/raptus/person/__init__.py
src/raptus/person/config.py
src/raptus/person/configure.zcml
src/raptus/person/factory.py
src/raptus/person/interfaces.py
src/raptus/person/browser/__init__.py
src/raptus/person/browser/configure.zcml
src/raptus/person/browser/person.pt
src/raptus/person/browser/person.py
src/raptus/person/browser/person_icon.png
src/raptus/person/browser/person_portlet.pt
src/raptus/person/browser/person_portlet.py
src/raptus/person/content/.DS_Store
src/raptus/person/content/__init__.py
src/raptus/person/content/configure.zcml
src/raptus/person/content/person.py
src/raptus/person/locales/raptus.person.pot
src/raptus/person/locales/de/LC_MESSAGES/raptus.person.mo
src/raptus/person/locales/de/LC_MESSAGES/raptus.person.po
src/raptus/person/locales/fr/LC_MESSAGES/raptus.person.mo
src/raptus/person/locales/fr/LC_MESSAGES/raptus.person.po
src/raptus/person/profiles/default/factory.py
src/raptus/person/profiles/default/factorytool.xml
src/raptus/person/profiles/default/portlets.xml
src/raptus/person/profiles/default/rolemap.xml
src/raptus/person/profiles/default/types.xml
src/raptus/person/profiles/default/types/Article.xml
src/raptus/person/profiles/default/types/Person.xml