Metadata-Version: 1.0
Name: raptus.person
Version: 1.0
Summary: Provides contenttype person
Home-page: http://svn.plone.org/svn/collective/
Author: UNKNOWN
Author-email: UNKNOWN
License: gpl
Platform: UNKNOWN
Classifier: Programming Language :: Python
